paddlex/.version
paddlex/__init__.py
paddlex/__main__.py
paddlex/constants.py
paddlex/engine.py
paddlex/hpip_links.html
paddlex/hpip_links_cu12.html
paddlex/model.py
paddlex/paddlex_cli.py
paddlex/version.py
paddlex/configs/modules/3d_bev_detection/BEVFusion.yaml
paddlex/configs/modules/chart_parsing/PP-Chart2Table.yaml
paddlex/configs/modules/doc_text_orientation/PP-LCNet_x1_0_doc_ori.yaml
paddlex/configs/modules/doc_vlm/PP-DocBee-2B.yaml
paddlex/configs/modules/doc_vlm/PP-DocBee-7B.yaml
paddlex/configs/modules/doc_vlm/PP-DocBee2-3B.yaml
paddlex/configs/modules/doc_vlm/PaddleOCR-VL-0.9B.yaml
paddlex/configs/modules/face_detection/BlazeFace-FPN-SSH.yaml
paddlex/configs/modules/face_detection/BlazeFace.yaml
paddlex/configs/modules/face_detection/PP-YOLOE_plus-S_face.yaml
paddlex/configs/modules/face_detection/PicoDet_LCNet_x2_5_face.yaml
paddlex/configs/modules/face_feature/MobileFaceNet.yaml
paddlex/configs/modules/face_feature/ResNet50_face.yaml
paddlex/configs/modules/formula_recognition/LaTeX_OCR_rec.yaml
paddlex/configs/modules/formula_recognition/PP-FormulaNet-L.yaml
paddlex/configs/modules/formula_recognition/PP-FormulaNet-S.yaml
paddlex/configs/modules/formula_recognition/PP-FormulaNet_plus-L.yaml
paddlex/configs/modules/formula_recognition/PP-FormulaNet_plus-M.yaml
paddlex/configs/modules/formula_recognition/PP-FormulaNet_plus-S.yaml
paddlex/configs/modules/formula_recognition/UniMERNet.yaml
paddlex/configs/modules/human_detection/PP-YOLOE-L_human.yaml
paddlex/configs/modules/human_detection/PP-YOLOE-S_human.yaml
paddlex/configs/modules/image_anomaly_detection/STFPM.yaml
paddlex/configs/modules/image_classification/CLIP_vit_base_patch16_224.yaml
paddlex/configs/modules/image_classification/CLIP_vit_large_patch14_224.yaml
paddlex/configs/modules/image_classification/ConvNeXt_base_224.yaml
paddlex/configs/modules/image_classification/ConvNeXt_base_384.yaml
paddlex/configs/modules/image_classification/ConvNeXt_large_224.yaml
paddlex-3.4.1.dist-info/licenses/LICENSE
paddlex-3.4.1.dist-info/METADATA
paddlex-3.4.1.dist-info/WHEEL
paddlex-3.4.1.dist-info/entry_points.txt
paddlex-3.4.1.dist-info/top_level.txt
paddlex-3.4.1.dist-info/RECORD
