Metadata-Version: 2.4
Name: paddlex
Version: 3.4.1
Summary: Low-code development tool based on PaddlePaddle.
Author: PaddlePaddle Authors
Author-email: 
License: Apache-2.0
Keywords: paddlepaddle
Classifier: Development Status :: 4 - Beta
Classifier: Intended Audience :: Developers
Classifier: Intended Audience :: Education
Classifier: Intended Audience :: Science/Research
Classifier: Programming Language :: Python :: 3.8
Classifier: Programming Language :: Python :: 3.9
Classifier: Programming Language :: Python :: 3.10
Classifier: Programming Language :: Python :: 3.11
Classifier: Programming Language :: Python :: 3.12
Classifier: Topic :: Scientific/Engineering
Classifier: Topic :: Scientific/Engineering :: Mathematics
Classifier: Topic :: Scientific/Engineering :: Artificial Intelligence
Classifier: Topic :: Software Development
Classifier: Topic :: Software Development :: Libraries
Classifier: Topic :: Software Development :: Libraries :: Python Modules
License-File: LICENSE
Requires-Dist: aistudio-sdk>=0.3.5
Requires-Dist: chardet
Requires-Dist: colorlog
Requires-Dist: filelock
Requires-Dist: huggingface-hub
Requires-Dist: modelscope>=1.28.0
Requires-Dist: numpy>=1.24
Requires-Dist: packaging
Requires-Dist: pandas>=1.3
Requires-Dist: pillow
Requires-Dist: prettytable
Requires-Dist: py-cpuinfo
Requires-Dist: pydantic>=2
Requires-Dist: PyYAML==6.0.2
Requires-Dist: requests
Requires-Dist: ruamel.yaml
Requires-Dist: typing-extensions
Requires-Dist: ujson
Provides-Extra: cv
Requires-Dist: faiss-cpu; extra == "cv"
Requires-Dist: matplotlib; extra == "cv"
Requires-Dist: opencv-contrib-python==4.10.0.84; extra == "cv"
Requires-Dist: pycocotools<=2.0.8; extra == "cv"
Requires-Dist: pypdfium2>=4; extra == "cv"
Requires-Dist: scikit-image; extra == "cv"
Provides-Extra: multimodal
Requires-Dist: einops; extra == "multimodal"
Requires-Dist: ftfy; extra == "multimodal"
Requires-Dist: GPUtil>=1.4; extra == "multimodal"
Requires-Dist: Jinja2; extra == "multimodal"
Requires-Dist: opencv-contrib-python==4.10.0.84; extra == "multimodal"
Requires-Dist: pypdfium2>=4; extra == "multimodal"
Requires-Dist: regex; extra == "multimodal"
Requires-Dist: safetensors>=0.7.0; extra == "multimodal"
Requires-Dist: sentencepiece; extra == "multimodal"
Requires-Dist: tiktoken; extra == "multimodal"
Provides-Extra: ie
Requires-Dist: ftfy; extra == "ie"
Requires-Dist: imagesize; extra == "ie"
Requires-Dist: langchain<1.0,>=0.2; extra == "ie"
Requires-Dist: langchain-community<1.0,>=0.2; extra == "ie"
Requires-Dist: langchain-core; extra == "ie"
Requires-Dist: langchain-openai<1.0,>=0.1; extra == "ie"
Requires-Dist: lxml; extra == "ie"
Requires-Dist: openai>=1.63; extra == "ie"
Requires-Dist: opencv-contrib-python==4.10.0.84; extra == "ie"
Requires-Dist: openpyxl; extra == "ie"
Requires-Dist: premailer; extra == "ie"
Requires-Dist: pyclipper; extra == "ie"
Requires-Dist: pypdfium2>=4; extra == "ie"
Requires-Dist: scikit-learn; extra == "ie"
Requires-Dist: scipy; extra == "ie"
Requires-Dist: shapely; extra == "ie"
Requires-Dist: tokenizers>=0.19; extra == "ie"
Provides-Extra: trans
Requires-Dist: beautifulsoup4; extra == "trans"
Requires-Dist: ftfy; extra == "trans"
Requires-Dist: imagesize; extra == "trans"
Requires-Dist: lxml; extra == "trans"
Requires-Dist: openai>=1.63; extra == "trans"
Requires-Dist: opencv-contrib-python==4.10.0.84; extra == "trans"
Requires-Dist: openpyxl; extra == "trans"
Requires-Dist: premailer; extra == "trans"
Requires-Dist: pyclipper; extra == "trans"
Requires-Dist: pypdfium2>=4; extra == "trans"
Requires-Dist: python-docx; extra == "trans"
Requires-Dist: scikit-learn; extra == "trans"
Requires-Dist: scipy; extra == "trans"
Requires-Dist: shapely; extra == "trans"
Requires-Dist: tokenizers>=0.19; extra == "trans"
Provides-Extra: ocr-core
Requires-Dist: imagesize; extra == "ocr-core"
Requires-Dist: opencv-contrib-python==4.10.0.84; extra == "ocr-core"
Requires-Dist: pyclipper; extra == "ocr-core"
Requires-Dist: pypdfium2>=4; extra == "ocr-core"
Requires-Dist: python-bidi; extra == "ocr-core"
Requires-Dist: shapely; extra == "ocr-core"
Provides-Extra: ocr
Requires-Dist: beautifulsoup4; extra == "ocr"
Requires-Dist: einops; extra == "ocr"
Requires-Dist: ftfy; extra == "ocr"
Requires-Dist: imagesize; extra == "ocr"
Requires-Dist: Jinja2; extra == "ocr"
Requires-Dist: lxml; extra == "ocr"
Requires-Dist: opencv-contrib-python==4.10.0.84; extra == "ocr"
Requires-Dist: openpyxl; extra == "ocr"
Requires-Dist: premailer; extra == "ocr"
Requires-Dist: pyclipper; extra == "ocr"
Requires-Dist: pypdfium2>=4; extra == "ocr"
Requires-Dist: python-bidi; extra == "ocr"
Requires-Dist: regex; extra == "ocr"
Requires-Dist: safetensors>=0.7.0; extra == "ocr"
Requires-Dist: scikit-learn; extra == "ocr"
Requires-Dist: scipy; extra == "ocr"
Requires-Dist: sentencepiece; extra == "ocr"
Requires-Dist: shapely; extra == "ocr"
Requires-Dist: tiktoken; extra == "ocr"
Requires-Dist: tokenizers>=0.19; extra == "ocr"
Provides-Extra: speech
Requires-Dist: ftfy; extra == "speech"
Requires-Dist: jieba; extra == "speech"
Requires-Dist: Jinja2; extra == "speech"
Requires-Dist: OpenCC; extra == "speech"
Requires-Dist: pypinyin; extra == "speech"
Requires-Dist: regex; extra == "speech"
Requires-Dist: soundfile; extra == "speech"
Requires-Dist: tqdm; extra == "speech"
Provides-Extra: ts
Requires-Dist: chinese-calendar; extra == "ts"
Requires-Dist: joblib; extra == "ts"
Requires-Dist: matplotlib; extra == "ts"
Requires-Dist: scikit-learn; extra == "ts"
Provides-Extra: video
Requires-Dist: decord==0.6.0; ((platform_machine == "x86_64" or platform_machine == "AMD64") and sys_platform != "darwin") and extra == "video"
Requires-Dist: opencv-contrib-python==4.10.0.84; extra == "video"
Provides-Extra: base
Requires-Dist: beautifulsoup4; extra == "base"
Requires-Dist: chinese-calendar; extra == "base"
Requires-Dist: decord==0.6.0; ((platform_machine == "x86_64" or platform_machine == "AMD64") and sys_platform != "darwin") and extra == "base"
Requires-Dist: einops; extra == "base"
Requires-Dist: faiss-cpu; extra == "base"
Requires-Dist: ftfy; extra == "base"
Requires-Dist: GPUtil>=1.4; extra == "base"
Requires-Dist: imagesize; extra == "base"
Requires-Dist: jieba; extra == "base"
Requires-Dist: Jinja2; extra == "base"
Requires-Dist: joblib; extra == "base"
Requires-Dist: langchain<1.0,>=0.2; extra == "base"
Requires-Dist: langchain-community<1.0,>=0.2; extra == "base"
Requires-Dist: langchain-core; extra == "base"
Requires-Dist: langchain-openai<1.0,>=0.1; extra == "base"
Requires-Dist: lxml; extra == "base"
Requires-Dist: matplotlib; extra == "base"
Requires-Dist: openai>=1.63; extra == "base"
Requires-Dist: OpenCC; extra == "base"
Requires-Dist: opencv-contrib-python==4.10.0.84; extra == "base"
Requires-Dist: openpyxl; extra == "base"
Requires-Dist: premailer; extra == "base"
Requires-Dist: pyclipper; extra == "base"
Requires-Dist: pycocotools<=2.0.8; extra == "base"
Requires-Dist: pypdfium2>=4; extra == "base"
Requires-Dist: pypinyin; extra == "base"
Requires-Dist: python-bidi; extra == "base"
Requires-Dist: python-docx; extra == "base"
Requires-Dist: regex; extra == "base"
Requires-Dist: safetensors>=0.7.0; extra == "base"
Requires-Dist: scikit-image; extra == "base"
Requires-Dist: scikit-learn; extra == "base"
Requires-Dist: scipy; extra == "base"
Requires-Dist: sentencepiece; extra == "base"
Requires-Dist: shapely; extra == "base"
Requires-Dist: soundfile; extra == "base"
Requires-Dist: tiktoken; extra == "base"
Requires-Dist: tokenizers>=0.19; extra == "base"
Requires-Dist: tqdm; extra == "base"
Provides-Extra: genai-client
Requires-Dist: openai>=1.63; extra == "genai-client"
Provides-Extra: genai-sglang-server
Requires-Dist: einops; extra == "genai-sglang-server"
Requires-Dist: sglang[all]==0.5.2; extra == "genai-sglang-server"
Requires-Dist: torch==2.8.0; extra == "genai-sglang-server"
Requires-Dist: transformers; extra == "genai-sglang-server"
Provides-Extra: genai-vllm-server
Requires-Dist: einops; extra == "genai-vllm-server"
Requires-Dist: torch==2.8.0; extra == "genai-vllm-server"
Requires-Dist: transformers<5.0.0; extra == "genai-vllm-server"
Requires-Dist: uvloop; extra == "genai-vllm-server"
Requires-Dist: vllm==0.10.2; extra == "genai-vllm-server"
Provides-Extra: paddle2onnx
Requires-Dist: paddle2onnx==2.0.2rc3; extra == "paddle2onnx"
Provides-Extra: serving
Requires-Dist: aiohttp>=3.9; extra == "serving"
Requires-Dist: bce-python-sdk>=0.9; extra == "serving"
Requires-Dist: fastapi>=0.110; extra == "serving"
Requires-Dist: filetype>=1.2; extra == "serving"
Requires-Dist: opencv-contrib-python==4.10.0.84; extra == "serving"
Requires-Dist: pypdfium2>=4; extra == "serving"
Requires-Dist: starlette>=0.36; extra == "serving"
Requires-Dist: uvicorn>=0.16; extra == "serving"
Requires-Dist: yarl>=1.9; extra == "serving"
Dynamic: author
Dynamic: classifier
Dynamic: description
Dynamic: description-content-type
Dynamic: keywords
Dynamic: license
Dynamic: license-file
Dynamic: provides-extra
Dynamic: requires-dist
Dynamic: summary
